atlantis_open_weather_mcp/__init__.py
atlantis_open_weather_mcp/weather_mcp_server.py
atlantis_open_weather_mcp-0.1.2.dist-info/WHEEL
atlantis_open_weather_mcp-0.1.2.dist-info/entry_points.txt
atlantis_open_weather_mcp-0.1.2.dist-info/METADATA
atlantis_open_weather_mcp-0.1.2.dist-info/RECORD
