Metadata-Version: 2.3
Name: atlantis-open-weather-mcp
Version: 0.1.2
Summary: An MCP server for OpenWeather data using uvx.
Requires-Dist: mcp[cli]>=1.18.0
Requires-Dist: requests>=2.32.3
Requires-Dist: pydantic>=2.11.3
Requires-Python: >=3.10
